.gitignore
README.rst
setup.py
cinq_collector_dns/__init__.py
cinq_collector_dns/views.py
cinq_collector_dns.egg-info/PKG-INFO
cinq_collector_dns.egg-info/SOURCES.txt
cinq_collector_dns.egg-info/dependency_links.txt
cinq_collector_dns.egg-info/entry_points.txt
cinq_collector_dns.egg-info/requires.txt
cinq_collector_dns.egg-info/top_level.txt